django_guard/__init__.py
django_guard/admin.py
django_guard/apps.py
django_guard/checker.py
django_guard/core/mem_report.py
django_guard/errors.py
django_guard/middleware.py
django_guard/migrations/__init__.py
django_guard/models.py
django_guard/templates/django_guard/503.html
django_guard/tests.py
django_guard/views.py
django_guard-0.1.1.dist-info/LICENSE
django_guard-0.1.1.dist-info/METADATA
django_guard-0.1.1.dist-info/WHEEL
django_guard-0.1.1.dist-info/RECORD
